{
    "Ar36": {
        "error": 0.0007001098793898736,
        "error_type": "SEM",
        "filter_outliers_dict": {
            "filter_outliers": true,
            "iterations": 2,
            "std_devs": 2
        },
        "fit": "Parabolic",
        "value": 0.003502719118545027
    },
    "Ar37": {
        "error": 0.013534986541731362,
        "error_type": "SEM",
        "filter_outliers_dict": {
            "filter_outliers": true,
            "iterations": 2,
            "std_devs": 2
        },
        "fit": "linear",
        "value": -0.06936596234797379
    },
    "Ar38": {
        "error": 0.004738657091647547,
        "error_type": "SEM",
        "filter_outliers_dict": {
            "filter_outliers": true,
            "iterations": 2,
            "std_devs": 2
        },
        "fit": "linear",
        "value": -0.023974851339716958
    },
    "Ar39": {
        "error": 0.013216189276738637,
        "error_type": "SEM",
        "filter_outliers_dict": {
            "filter_outliers": true,
            "iterations": 2,
            "std_devs": 2
        },
        "fit": "Parabolic",
        "value": 0.002613785051354992
    },
    "Ar40": {
        "error": 0.027919128522731658,
        "error_type": "SEM",
        "filter_outliers_dict": {
            "filter_outliers": true,
            "iterations": 2,
            "std_devs": 2
        },
        "fit": "Parabolic",
        "value": 0.09380018186926525
    }
}