{
    "Ar36": {
        "error": 0.0001465980666847185,
        "error_type": "SEM",
        "filter_outliers_dict": {
            "filter_outliers": true,
            "iterations": 1,
            "std_devs": 2
        },
        "fit": "Parabolic",
        "fn": 321,
        "include_baseline_error": false,
        "n": 340,
        "reviewed": true,
        "value": 0.00038586503712399083
    },
    "Ar37": {
        "error": 0.015177216768620017,
        "error_type": "SEM",
        "filter_outliers_dict": {
            "filter_outliers": true,
            "iterations": 1,
            "std_devs": 2
        },
        "fit": "Linear",
        "fn": 323,
        "include_baseline_error": false,
        "n": 340,
        "reviewed": true,
        "value": -0.10054034166712786
    },
    "Ar38": {
        "error": 0.005975445132518374,
        "error_type": "SEM",
        "filter_outliers_dict": {
            "filter_outliers": true,
            "iterations": 1,
            "std_devs": 2
        },
        "fit": "Linear",
        "fn": 323,
        "include_baseline_error": false,
        "n": 340,
        "reviewed": true,
        "value": 0.10523717968296589
    },
    "Ar39": {
        "error": 0.01566827584084249,
        "error_type": "SEM",
        "filter_outliers_dict": {
            "filter_outliers": true,
            "iterations": 1,
            "std_devs": 2
        },
        "fit": "Parabolic",
        "fn": 332,
        "include_baseline_error": false,
        "n": 340,
        "reviewed": true,
        "value": -0.002984686152297832
    },
    "Ar40": {
        "error": 0.027236587249458398,
        "error_type": "SEM",
        "filter_outliers_dict": {
            "filter_outliers": true,
            "iterations": 1,
            "std_devs": 2
        },
        "fit": "Parabolic",
        "fn": 323,
        "include_baseline_error": false,
        "n": 340,
        "reviewed": true,
        "value": 0.26984479941828093
    }
}