{
    "Ar36": {
        "error": 0.006125996955148097,
        "error_type": "SEM",
        "filter_outliers_dict": {
            "filter_outliers": true,
            "iterations": 1,
            "std_devs": 2
        },
        "fit": "Parabolic",
        "fn": 325,
        "include_baseline_error": false,
        "n": 340,
        "reviewed": true,
        "value": 4.943616812385915
    },
    "Ar37": {
        "error": 0.014492053671798968,
        "error_type": "SEM",
        "filter_outliers_dict": {
            "filter_outliers": true,
            "iterations": 1,
            "std_devs": 2
        },
        "fit": "Linear",
        "fn": 324,
        "include_baseline_error": false,
        "n": 340,
        "reviewed": true,
        "value": -0.09437623277098299
    },
    "Ar38": {
        "error": 0.005282102266790741,
        "error_type": "SEM",
        "filter_outliers_dict": {
            "filter_outliers": true,
            "iterations": 1,
            "std_devs": 2
        },
        "fit": "Linear",
        "fn": 320,
        "include_baseline_error": false,
        "n": 340,
        "reviewed": true,
        "value": 1.016958439981106
    },
    "Ar39": {
        "error": 0.013851956015164904,
        "error_type": "SEM",
        "filter_outliers_dict": {
            "filter_outliers": true,
            "iterations": 1,
            "std_devs": 2
        },
        "fit": "Parabolic",
        "fn": 325,
        "include_baseline_error": false,
        "n": 340,
        "reviewed": true,
        "value": -0.01937784184119505
    },
    "Ar40": {
        "error": 0.1210533832935033,
        "error_type": "SEM",
        "filter_outliers_dict": {
            "filter_outliers": true,
            "iterations": 1,
            "std_devs": 2
        },
        "fit": "Parabolic",
        "fn": 320,
        "include_baseline_error": false,
        "n": 340,
        "reviewed": true,
        "value": 1471.1289954307667
    }
}