{
    "Ar36": {
        "error": 0.00592247321191847,
        "error_type": "SEM",
        "filter_outliers_dict": {
            "filter_outliers": true,
            "iterations": 1,
            "std_devs": 2
        },
        "fit": "Parabolic",
        "fn": 325,
        "include_baseline_error": false,
        "n": 340,
        "reviewed": true,
        "value": 4.755838678838899
    },
    "Ar37": {
        "error": 0.016511101365502864,
        "error_type": "SEM",
        "filter_outliers_dict": {
            "filter_outliers": true,
            "iterations": 1,
            "std_devs": 2
        },
        "fit": "Linear",
        "fn": 325,
        "include_baseline_error": false,
        "n": 340,
        "reviewed": true,
        "value": -0.12085966701907844
    },
    "Ar38": {
        "error": 0.005203581834124851,
        "error_type": "SEM",
        "filter_outliers_dict": {
            "filter_outliers": true,
            "iterations": 1,
            "std_devs": 2
        },
        "fit": "Linear",
        "fn": 325,
        "include_baseline_error": false,
        "n": 340,
        "reviewed": true,
        "value": 0.9840148179015022
    },
    "Ar39": {
        "error": 0.015347084775045339,
        "error_type": "SEM",
        "filter_outliers_dict": {
            "filter_outliers": true,
            "iterations": 1,
            "std_devs": 2
        },
        "fit": "Parabolic",
        "fn": 326,
        "include_baseline_error": false,
        "n": 340,
        "reviewed": true,
        "value": -0.0408728367527693
    },
    "Ar40": {
        "error": 0.11500780661182222,
        "error_type": "SEM",
        "filter_outliers_dict": {
            "filter_outliers": true,
            "iterations": 1,
            "std_devs": 2
        },
        "fit": "Parabolic",
        "fn": 331,
        "include_baseline_error": false,
        "n": 340,
        "reviewed": true,
        "value": 1405.908616219876
    }
}